coveo_example_library/__init__.py
coveo_example_library/example.py
coveo_example_library/py.typed
coveo_example_library-0.0.8.dist-info/WHEEL
coveo_example_library-0.0.8.dist-info/METADATA
coveo_example_library-0.0.8.dist-info/RECORD
